thriftpy_cli/__init__.py
thriftpy_cli/cmd.py
thriftpy_cli-0.3.dist-info/METADATA
thriftpy_cli-0.3.dist-info/WHEEL
thriftpy_cli-0.3.dist-info/entry_points.txt
thriftpy_cli-0.3.dist-info/top_level.txt
thriftpy_cli-0.3.dist-info/RECORD
