Metadata-Version: 2.1
Name: thriftpy-cli
Version: 0.3
Summary: Commandline tools for thrift
Home-page: https://github.com/wooparadog/thriftpy-cli/
Author: Haochuan Guo
Author-email: guohaochuan@gmail.com
License: UNKNOWN
Platform: UNKNOWN
Requires-Dist: click
Requires-Dist: thriftpy
Requires-Dist: ipython (==5.8.0)
